dataprovider/__init__.py
dataprovider/sdk/__init__.py
dataprovider/sdk/client/__init__.py
dataprovider/sdk/client/api_client.py
dataprovider_sdk-1.0.0.dist-info/licenses/LICENSE
dataprovider_sdk-1.0.0.dist-info/METADATA
dataprovider_sdk-1.0.0.dist-info/WHEEL
dataprovider_sdk-1.0.0.dist-info/top_level.txt
dataprovider_sdk-1.0.0.dist-info/RECORD
