Metadata-Version: 2.4
Name: dataprovider-sdk
Version: 1.0.0
Summary: A lightweight SDK for interacting with the Dataprovider.com API.
Author-email: "Dataprovider.com" <info@dataprovider.com>
Requires-Python: >=3.13
License-File: LICENSE
Requires-Dist: requests>=2.32.4
Dynamic: license-file
